whateat/__init__.py
whateat/__main__.py
whateat/cli/__init__.py
whateat/cli/main.py
whateat-0.0.1.data/scripts/whateat
whateat-0.0.1.dist-info/LICENSE
whateat-0.0.1.dist-info/METADATA
whateat-0.0.1.dist-info/WHEEL
whateat-0.0.1.dist-info/top_level.txt
whateat-0.0.1.dist-info/RECORD
