Metadata-Version: 2.1
Name: whateat
Version: 0.0.1
Summary: what should i eat?
Home-page: https://github.com/azye/whateat
Author: Alex Ye
Author-email: alexzye1@gmail.com
License: UNKNOWN
Platform: UNKNOWN
Requires-Python: >=3.6
